AUTHORS
CHANGES
LICENSE
MANIFEST.in
README.rst
setup.py
django_user_tracking.egg-info/PKG-INFO
django_user_tracking.egg-info/SOURCES.txt
django_user_tracking.egg-info/dependency_links.txt
django_user_tracking.egg-info/top_level.txt
tracking/__init__.py
tracking/admin.py
tracking/listeners.py
tracking/middleware.py
tracking/models.py
tracking/settings.py
tracking/tests.py
tracking/urls.py
tracking/utils.py
tracking/views.py
tracking/locale/de/LC_MESSAGES/django.mo
tracking/locale/de/LC_MESSAGES/django.po
tracking/media/tracking/img/Flags.zip
tracking/media/tracking/img/famfamfam_flag_icons.zip
tracking/media/tracking/js/jquery-1.4.4.min.js
tracking/media/tracking/js/jquery-2.0.3.js
tracking/templates/base.html
tracking/templates/tracking/_active_users.html
tracking/templates/tracking/_active_users.js
tracking/templates/tracking/refresh_active_users.js
tracking/templates/tracking/visitor_map.html
tracking/templatetags/__init__.py
tracking/templatetags/tracking_tags.py