Metadata-Version: 1.1
Name: django-user-tracking
Version: 0.4.11
Summary: Basic visitor tracking and blacklisting for Django
Home-page: http://bitbucket.org/elevenbits/django-user-tracking
Author: Jan Willems
Author-email: jw@elevenbits.com
License: MIT
Keywords: django,tracking,visitors
Platform: UNKNOWN
Classifier: Development Status :: 5 - Production/Stable
Classifier: Environment :: Web Environment
Classifier: Framework :: Django
Classifier: Intended Audience :: Developers
Classifier: Intended Audience :: Information Technology
Classifier: Intended Audience :: System Administrators
Classifier: License :: OSI Approved :: MIT License
Classifier: Natural Language :: English
Classifier: Operating System :: OS Independent
Classifier: Programming Language :: Python
Classifier: Programming Language :: Python :: 3.4
Classifier: Topic :: Internet :: Log Analysis
Classifier: Topic :: Internet :: WWW/HTTP :: Dynamic Content :: Page Counters
Classifier: Topic :: Internet :: WWW/HTTP :: WSGI :: Middleware
Classifier: Topic :: Security
Classifier: Topic :: System :: Monitoring
Classifier: Topic :: Utilities
